dreegdl/__init__.py
dreegdl/config.py
dreegdl/kaggle.py
dreegdl/model.py
dreegdl/preprocessing.py
dreegdl/smote.py
dreegdl/training.py
dreegdl/utils.py
dreegdl-1.0.0.dist-info/LICENSE
dreegdl-1.0.0.dist-info/METADATA
dreegdl-1.0.0.dist-info/WHEEL
dreegdl-1.0.0.dist-info/top_level.txt
dreegdl-1.0.0.dist-info/RECORD
